create_rf/RandomFeaturesGenerator.py
create_rf/__init__.py
create_rf/aux.py
create_rf/gen_rf_factors.py
create_rf/pre_process_130.py
didipack/__init__.py
didipack/latex_paper.py
didipack/latex_ressource.py
didipack/latex_table.py
didipack/parameters.py
didipack/plot_function.py
didipack/create_rf/RandomFeaturesGenerator.py
didipack/create_rf/__init__.py
didipack/create_rf/aux.py
didipack/create_rf/gen_rf_factors.py
didipack/create_rf/pre_process_130.py
didipack/trainer/__init__.py
didipack/trainer/train_splitter.py
didipack/trainer/trainer_abstract.py
didipack/trainer/trainer_logistic_elastic_net.py
didipack/trainer/trainer_ridge.py
didipack/utils/__init__.py
didipack/utils/general.py
didipack/utils/pandasplus.py
didipack/utils/plot.py
didipack/utils/ridge.py
didipack/utils/smart_algebra.py
didipack/utils_didi/__init__.py
didipack/utils_didi/general.py
didipack/utils_didi/ols.py
didipack/utils_didi/pandasplus.py
didipack/utils_didi/parser.py
didipack/utils_didi/plot.py
didipack/utils_didi/ridge.py
didipack/utils_didi/smart_algebra.py
trainer/__init__.py
trainer/train_splitter.py
trainer/trainer_abstract.py
trainer/trainer_ridge.py
utils/__init__.py
utils/general.py
utils/pandasplus.py
utils/plot.py
utils/ridge.py
utils/smart_algebra.py
didipack-4.3.22.dist-info/LICENSE.txt
didipack-4.3.22.dist-info/METADATA
didipack-4.3.22.dist-info/WHEEL
didipack-4.3.22.dist-info/top_level.txt
didipack-4.3.22.dist-info/RECORD
