Metadata-Version: 2.1
Name: didipack
Version: 4.3.22
Summary: Usefull time saver for data-science and finance with python
Home-page: https://github.com/AntoineDidisheim
Download-URL: https://github.com/AntoineDidisheim/didipack/archive/v0.1.1.tar.gz
Author: Antoine Didisheim
Author-email: antoinedidisheim@gmail.com
License: MIT
Keywords: LaTex,Finance
Classifier: Development Status :: 3 - Alpha
Classifier: Intended Audience :: Developers
Classifier: Topic :: Software Development :: Build Tools
Classifier: License :: OSI Approved :: MIT License
Classifier: Programming Language :: Python :: 3.4
Classifier: Programming Language :: Python :: 3.5
Classifier: Programming Language :: Python :: 3.6
Classifier: Programming Language :: Python :: 3.7
Classifier: Programming Language :: Python :: 3.8
License-File: LICENSE.txt
Requires-Dist: numpy
Requires-Dist: pandas
Requires-Dist: statsmodels
Requires-Dist: matplotlib
Requires-Dist: jinja2
Requires-Dist: tqdm
Requires-Dist: scikit-learn
